awdur/__init__.py
awdur/cli/__init__.py
awdur/cli/_core.py
awdur/cli/bind.py
awdur/cli/export.py
awdur-0.0.1.dist-info/METADATA
awdur-0.0.1.dist-info/WHEEL
awdur-0.0.1.dist-info/entry_points.txt
awdur-0.0.1.dist-info/RECORD
